{"rights":[{"rightType":"Download","origin":{"originType":"KindleUnlimited"},"rightStatus":"Revoked","acquiredDate":"2024-03-08T19:03:10.869Z","consumptions":[{"resourceItemType":"Content","targetEntity":{"entityType":"Device"},"startDate":"2024-03-08T20:06:33.941Z"},{"resourceItemType":"XraySidecar","targetEntity":{"entityType":"Device"},"startDate":"2024-03-08T20:16:18.440Z"},{"resourceItemType":"XraySidecar","targetEntity":{"entityType":"Device"},"startDate":"2024-03-08T19:03:22.522Z"},{"resourceItemType":"Content","targetEntity":{"entityType":"Device"}}]}],"lastUpdatedDate":"2024-03-11T07:02:20.893Z","resource":{"resourceType":"KindleEBook","catalog":"Amazon","ASIN":"B01D6TA9Y8"},"entity":{"entityType":"Customer"}}