{"rights":[{"rightType":"Download","origin":{"originType":"KindleUnlimited"},"rightStatus":"Revoked","acquiredDate":"2025-03-14T17:57:48.974Z","consumptions":[{"resourceItemType":"XraySidecar","targetEntity":{"entityType":"Device"},"startDate":"2025-03-14T18:01:58.072Z"},{"resourceItemType":"Content","targetEntity":{"entityType":"Device"}}]}],"lastUpdatedDate":"2025-03-23T02:55:02.189Z","resource":{"resourceType":"KindleEBook","catalog":"Amazon","ASIN":"B09QK389GG","Product Name":"Consider Me (Playing For Keeps Book 1)"},"entity":{"entityType":"Customer"}}