{"rights":[{"rightType":"Download","origin":{"originType":"Sharing"},"rightStatus":"Active","acquiredDate":"2025-10-19T16:06:10.614Z","consumptions":[{"resourceItemType":"XraySidecar","targetEntity":{"entityType":"Device"},"startDate":"2025-10-21T20:47:53.459Z"},{"resourceItemType":"Content","targetEntity":{"entityType":"Device"},"startDate":"2025-10-20T20:38:07.085Z"},{"resourceItemType":"XraySidecar","targetEntity":{"entityType":"Device"},"startDate":"2025-10-19T18:14:26.401Z"},{"resourceItemType":"Content","targetEntity":{"entityType":"Device"},"startDate":"2025-10-19T18:14:17.177Z"},{"resourceItemType":"Content","targetEntity":{"entityType":"Device"}}]}],"lastUpdatedDate":"2025-10-19T16:06:11.319Z","resource":{"resourceType":"KindleEBook","catalog":"Amazon","ASIN":"B000YI1K0C","Product Name":"Looking for Alaska"},"entity":{"entityType":"Customer"}}