{"rights":[{"rightType":"Download","origin":{"originType":"KindleUnlimited"},"rightStatus":"Revoked","acquiredDate":"2024-03-08T18:48:51.312Z","consumptions":[{"resourceItemType":"XraySidecar","targetEntity":{"entityType":"Device"},"startDate":"2024-03-08T18:56:56.815Z"},{"resourceItemType":"Content","targetEntity":{"entityType":"Device"},"startDate":"2024-03-08T18:56:17.412Z"},{"resourceItemType":"XraySidecar","targetEntity":{"entityType":"Device"},"startDate":"2024-03-08T18:53:54.156Z"},{"resourceItemType":"Content","targetEntity":{"entityType":"Device"},"startDate":"2024-03-08T18:53:39.685Z"}]},{"rightType":"Download","origin":{"originType":"KindleUnlimited"},"rightStatus":"Revoked","acquiredDate":"2024-03-03T07:07:51.147Z","consumptions":[{"resourceItemType":"XraySidecar","targetEntity":{"entityType":"Device"},"startDate":"2024-03-03T07:24:31.241Z"},{"resourceItemType":"Content","targetEntity":{"entityType":"Device"}}]}],"lastUpdatedDate":"2024-04-26T20:14:49.463Z","resource":{"resourceType":"KindleEBook","catalog":"Amazon","ASIN":"B0BCHJ9885","Product Name":"Make Me: A Dark Crime Syndicate Romance (The Fox Family Crime Syndicate Book 1)"},"entity":{"entityType":"Customer"}}